Metadata-Version: 2.1
Name: userful
Version: 0.1.0
Summary: Unofficial python client for userful API
Home-page: https://github.com/SpinifexGroup/python-userful
Author: Spinifex Group
Author-email: justin.crown@spinifexgroup.com
License: MIT
Keywords: userful
Platform: UNKNOWN
Classifier: Development Status :: 2 - Pre-Alpha
Classifier: Intended Audience :: Developers
Classifier: License :: OSI Approved :: MIT License
Classifier: Natural Language :: English
Classifier: Programming Language :: Python :: 3
